pyAttributes/ArgParseAttributes.py
pyAttributes/__init__.py
pyAttributes-2.5.1.dist-info/LICENSE.md
pyAttributes-2.5.1.dist-info/METADATA
pyAttributes-2.5.1.dist-info/WHEEL
pyAttributes-2.5.1.dist-info/top_level.txt
pyAttributes-2.5.1.dist-info/RECORD
