Metadata-Version: 2.1
Name: pyAttributes
Version: 2.5.1
Summary: .NET-like Attributes implemented as Python decorators.
Home-page: https://GitHub.com/pyTooling/pyAttributes
Author: Patrick Lehmann
Author-email: Paebbels@gmail.com
License: Apache-2.0
Project-URL: Documentation, https://pyTooling.GitHub.io/pyAttributes
Project-URL: Source Code, https://GitHub.com/pyTooling/pyAttributes
Project-URL: Issue Tracker, https://GitHub.com/pyTooling/pyAttributes/issues
Keywords: decorators,attributes,argparse
Platform: UNKNOWN
Classifier: Operating System :: OS Independent
Classifier: Intended Audience :: Developers
Classifier: Topic :: Utilities
Classifier: License :: OSI Approved :: Apache Software License
Classifier: Programming Language :: Python :: 3 :: Only
Classifier: Programming Language :: Python :: 3.7
Classifier: Programming Language :: Python :: 3.8
Classifier: Programming Language :: Python :: 3.9
Classifier: Programming Language :: Python :: 3.10
Classifier: Development Status :: 5 - Production/Stable
Requires-Python: >=3.7
License-File: LICENSE.md
Requires-Dist: pyTooling (>=1.9.5)
Requires-Dist: argcomplete (>=1.12.3)
Provides-Extra: all
Requires-Dist: argcomplete (>=1.12.3) ; extra == 'all'
Requires-Dist: sphinxcontrib-mermaid (>=0.7.1) ; extra == 'all'
Requires-Dist: sphinx-fontawesome (>=0.0.6) ; extra == 'all'
Requires-Dist: pyTooling (>=1.9.5) ; extra == 'all'
Requires-Dist: autoapi ; extra == 'all'
Requires-Dist: sphinx (>=4.4.0) ; extra == 'all'
Requires-Dist: sphinx-autodoc-typehints (>=1.17.0) ; extra == 'all'
Provides-Extra: doc
Requires-Dist: argcomplete (>=1.12.3) ; extra == 'doc'
Requires-Dist: sphinxcontrib-mermaid (>=0.7.1) ; extra == 'doc'
Requires-Dist: sphinx-fontawesome (>=0.0.6) ; extra == 'doc'
Requires-Dist: pyTooling (>=1.9.5) ; extra == 'doc'
Requires-Dist: autoapi ; extra == 'doc'
Requires-Dist: sphinx (>=4.4.0) ; extra == 'doc'
Requires-Dist: sphinx-autodoc-typehints (>=1.17.0) ; extra == 'doc'
